{
    "fluentMethods": true,
    "relationships": [
        {
            "relationshipName": "filiere",
            "otherEntityName": "filiere",
            "relationshipType": "many-to-one",
            "otherEntityField": "id"
        }
    ],
    "fields": [
        {
            "fieldName": "annee",
            "fieldType": "ZonedDateTime",
            "fieldValidateRules": [
                "required"
            ]
        }
    ],
    "changelogDate": "20170125144914",
    "entityTableName": "promotion",
    "dto": "mapstruct",
    "pagination": "no",
    "service": "serviceImpl"
}